{"meta":{"schema_version":1,"tab":"finance","generated_utc":"2026-07-01T16:51:38Z","hints":{"total_marco":"Visão geral por Data/Conta — gráficos executivos.","detalhado_marco":"Auditoria por Grupo_Gasto / categoria."},"csv_sources":{"total":"conf_total_marco.csv","detalhado":"conf_detalhado_marco.csv"}},"total_marco":[{"Conta":"NS","Categoria":"Recuperação","Data":"2026-07-01","Gasto USD":"17.15","SMS_Transactions":"2399"},{"Conta":"Joao","Categoria":"Broadcast","Data":"2026-07-01","Gasto USD":"7.91","SMS_Transactions":"788"},{"Conta":"Bernardo","Categoria":"Broadcast","Data":"2026-07-01","Gasto USD":"4.65","SMS_Transactions":"812"},{"Conta":"Rafa","Categoria":"Broadcast","Data":"2026-07-01","Gasto USD":"0.01","SMS_Transactions":"1"},{"Conta":"Havenmove","Categoria":"Standby","Data":"2026-07-01","Gasto USD":"14.14","SMS_Transactions":"2632"},{"Conta":"Rehableaf","Categoria":"Standby","Data":"2026-07-01","Gasto USD":"2.28","SMS_Transactions":"22"},{"Conta":"Richard","Categoria":"Standby","Data":"2026-07-01","Gasto USD":"5.37","SMS_Transactions":"812"},{"Conta":"Naturemove","Categoria":"Standby","Data":"2026-07-01","Gasto USD":"0.21","SMS_Transactions":"39"}],"detalhado_marco":[{"Data":"2026-07-01","Conta":"Richard","Categoria":"Standby","Grupo_Gasto":"SMS: Envio/Recebimento","Valor_USD":"0.012"},{"Data":"2026-07-01","Conta":"Richard","Categoria":"Standby","Grupo_Gasto":"Voz: Chamadas e Minutos","Valor_USD":"0.506"},{"Data":"2026-07-01","Conta":"Richard","Categoria":"Standby","Grupo_Gasto":"IA: Transcrição e Speech","Valor_USD":"0.273"},{"Data":"2026-07-01","Conta":"Naturemove","Categoria":"Standby","Grupo_Gasto":"SMS: Envio/Recebimento","Valor_USD":"0.003"},{"Data":"2026-07-01","Conta":"Joao","Categoria":"Broadcast","Grupo_Gasto":"SMS: Envio/Recebimento","Valor_USD":"0.012"},{"Data":"2026-07-01","Conta":"Joao","Categoria":"Broadcast","Grupo_Gasto":"Voz: Chamadas e Minutos","Valor_USD":"0.044"},{"Data":"2026-07-01","Conta":"Joao","Categoria":"Broadcast","Grupo_Gasto":"Voz: Gravações e Storage","Valor_USD":"0.225"},{"Data":"2026-07-01","Conta":"Joao","Categoria":"Broadcast","Grupo_Gasto":"IA: Transcrição e Speech","Valor_USD":"0.026"},{"Data":"2026-07-01","Conta":"Joao","Categoria":"Broadcast","Grupo_Gasto":"Segurança: Lookups e Verify","Valor_USD":"0.0"},{"Data":"2026-07-01","Conta":"Havenmove","Categoria":"Standby","Grupo_Gasto":"Voz: Chamadas e Minutos","Valor_USD":"0.0"},{"Data":"2026-07-01","Conta":"Havenmove","Categoria":"Standby","Grupo_Gasto":"IA: Transcrição e Speech","Valor_USD":"0.585"},{"Data":"2026-07-01","Conta":"Bernardo","Categoria":"Broadcast","Grupo_Gasto":"SMS: Envio/Recebimento","Valor_USD":"0.003"}]}