{"meta":{"schema_version":1,"tab":"saldo","generated_utc":"2026-05-06T00:41:30Z","hints":{"accounts":"Uma linha por Conta — Saldo_USD atual."},"csv_sources":{"saldo":"conf_saldos.csv"}},"accounts":[{"Conta":"Joao","Categoria":"Broadcast","Saldo_USD":"1072.8","Moeda":"USD","Atualizado_Em":"2026-05-05 23:39 UTC"},{"Conta":"Bernardo","Categoria":"Broadcast","Saldo_USD":"1447.47","Moeda":"USD","Atualizado_Em":"2026-05-05 23:39 UTC"},{"Conta":"Rafa","Categoria":"Broadcast","Saldo_USD":"1484.04","Moeda":"USD","Atualizado_Em":"2026-05-05 23:39 UTC"},{"Conta":"Havenmove","Categoria":"Standby","Saldo_USD":"1996.97","Moeda":"USD","Atualizado_Em":"2026-05-05 23:39 UTC"},{"Conta":"Rehableaf","Categoria":"Standby","Saldo_USD":"-13.4","Moeda":"USD","Atualizado_Em":"2026-05-05 23:39 UTC"},{"Conta":"Richard","Categoria":"Standby","Saldo_USD":"883.37","Moeda":"USD","Atualizado_Em":"2026-05-05 23:39 UTC"},{"Conta":"Naturemove","Categoria":"Standby","Saldo_USD":"760.84","Moeda":"USD","Atualizado_Em":"2026-05-05 23:39 UTC"}]}