{"meta":{"schema_version":1,"tab":"saldo","generated_utc":"2026-05-13T23:11:32Z","hints":{"accounts":"Uma linha por Conta — Saldo_USD atual."},"csv_sources":{"saldo":"conf_saldos.csv"}},"accounts":[{"Conta":"Joao","Categoria":"Broadcast","Saldo_USD":"302.02","Moeda":"USD","Atualizado_Em":"2026-05-13 22:49 UTC"},{"Conta":"Bernardo","Categoria":"Broadcast","Saldo_USD":"7964.5","Moeda":"USD","Atualizado_Em":"2026-05-13 22:49 UTC"},{"Conta":"Rafa","Categoria":"Broadcast","Saldo_USD":"1481.52","Moeda":"USD","Atualizado_Em":"2026-05-13 22:49 UTC"},{"Conta":"Havenmove","Categoria":"Standby","Saldo_USD":"919.81","Moeda":"USD","Atualizado_Em":"2026-05-13 22:49 UTC"},{"Conta":"Rehableaf","Categoria":"Standby","Saldo_USD":"-13.4","Moeda":"USD","Atualizado_Em":"2026-05-13 22:49 UTC"},{"Conta":"Richard","Categoria":"Standby","Saldo_USD":"784.1","Moeda":"USD","Atualizado_Em":"2026-05-13 22:49 UTC"},{"Conta":"Naturemove","Categoria":"Standby","Saldo_USD":"750.23","Moeda":"USD","Atualizado_Em":"2026-05-13 22:49 UTC"}]}