{"meta":{"schema_version":1,"tab":"saldo","generated_utc":"2026-07-22T23:33:24Z","hints":{"accounts":"Uma linha por Conta — Saldo_USD atual."},"csv_sources":{"saldo":"conf_saldos.csv"}},"accounts":[{"Conta":"NS","Categoria":"Recuperação","Saldo_USD":"837.57","Moeda":"USD","Atualizado_Em":"2026-07-22 23:14 UTC"},{"Conta":"Joao","Categoria":"Broadcast","Saldo_USD":"455.95","Moeda":"USD","Atualizado_Em":"2026-07-22 23:14 UTC"},{"Conta":"Bernardo","Categoria":"Broadcast","Saldo_USD":"20591.43","Moeda":"USD","Atualizado_Em":"2026-07-22 23:14 UTC"},{"Conta":"Rafa","Categoria":"Broadcast","Saldo_USD":"293.03","Moeda":"USD","Atualizado_Em":"2026-07-22 23:14 UTC"},{"Conta":"Havenmove","Categoria":"Standby","Saldo_USD":"129.2","Moeda":"USD","Atualizado_Em":"2026-07-22 23:14 UTC"},{"Conta":"Rehableaf","Categoria":"Standby","Saldo_USD":"522.35","Moeda":"USD","Atualizado_Em":"2026-07-22 23:14 UTC"},{"Conta":"Richard","Categoria":"Standby","Saldo_USD":"454.66","Moeda":"USD","Atualizado_Em":"2026-07-22 23:14 UTC"},{"Conta":"Naturemove","Categoria":"Standby","Saldo_USD":"16717.12","Moeda":"USD","Atualizado_Em":"2026-07-22 23:14 UTC"}]}